pydruid/__init__.py
pydruid/async_client.py
pydruid/client.py
pydruid/query.py
pydruid/utils/__init__.py
pydruid/utils/aggregators.py
pydruid/utils/dimensions.py
pydruid/utils/filters.py
pydruid/utils/having.py
pydruid/utils/postaggregator.py
pydruid/utils/query_utils.py
pydruid-0.3.1.dist-info/DESCRIPTION.rst
pydruid-0.3.1.dist-info/METADATA
pydruid-0.3.1.dist-info/RECORD
pydruid-0.3.1.dist-info/WHEEL
pydruid-0.3.1.dist-info/metadata.json
pydruid-0.3.1.dist-info/top_level.txt
